yahtzee/__init__.py
yahtzee/dice.py
yahtzee/game.py
yahtzee/game_player.py
yahtzee/game_state_values.pkl
yahtzee/iterators.py
yahtzee/payoffs.py
yahtzee/play_game.py
yahtzee/run_solver.py
yahtzee/solve.py
yahtzee_solve-0.0.1.dist-info/LICENSE.txt
yahtzee_solve-0.0.1.dist-info/METADATA
yahtzee_solve-0.0.1.dist-info/WHEEL
yahtzee_solve-0.0.1.dist-info/entry_points.txt
yahtzee_solve-0.0.1.dist-info/top_level.txt
yahtzee_solve-0.0.1.dist-info/RECORD
