Metadata-Version: 2.1
Name: yahtzee-solve
Version: 0.0.1
Summary: A package and command line tool for Yahtzee
Home-page: https://github.com/dpmerrell/yahtzee
Author: David Merrell
Author-email: davidpmerrell@gmail.com
License: UNKNOWN
Platform: UNKNOWN
Requires-Python: >=3.8
License-File: LICENSE.txt
